mhealth_datasets_upload/__init__.py
mhealth_datasets_upload/config.py
mhealth_datasets_upload/upload.py
mhealth_datasets_upload-0.8.dist-info/LICENSE
mhealth_datasets_upload-0.8.dist-info/METADATA
mhealth_datasets_upload-0.8.dist-info/WHEEL
mhealth_datasets_upload-0.8.dist-info/top_level.txt
mhealth_datasets_upload-0.8.dist-info/RECORD
